webshoes/PROJECT.txt
webshoes/__init__.py
webshoes/webshoes.py
webshoes/web/webshoes.js
webshoes-0.1.5.dist-info/LICENSE
webshoes-0.1.5.dist-info/METADATA
webshoes-0.1.5.dist-info/WHEEL
webshoes-0.1.5.dist-info/top_level.txt
webshoes-0.1.5.dist-info/RECORD
