Metadata-Version: 2.1
Name: webshoes
Version: 0.1.5
Summary: Quickly create a web service supporting both websockets and http.
Home-page: https://github.com/wheresjames/webshoes
Author: Robert Umbehant
Author-email: webshoes@wheresjames.com
License: MIT
Platform: UNKNOWN
License-File: LICENSE
Requires-Dist: aiohttp
Requires-Dist: propertybag
Requires-Dist: sparen
Requires-Dist: threadmsg (>=0.2.0)
